CHANGES
LICENSE
MANIFEST.in
README.rst
setup.py
demos/all.py
demos/certificate.pem
demos/logging_proxy.py
demos/privatekey.pem
demos/ssl2ssl.py
demos/ssl2tcp.py
demos/tcp2ssl.py
demos/tcp2tcp.py
maproxy/__init__.py
maproxy/iomanager.py
maproxy/proxyserver.py
maproxy/session.py
maproxy.egg-info/PKG-INFO
maproxy.egg-info/SOURCES.txt
maproxy.egg-info/dependency_links.txt
maproxy.egg-info/requires.txt
maproxy.egg-info/top_level.txt