Metadata-Version: 1.1
Name: maproxy
Version: 0.0.12
Summary: My first attempt to create a simple and awesome TCP proxy using Tornado
Home-page: UNKNOWN
Author: Zvika Ferentz
Author-email: zvika dot ferentz at gmail
License: UNKNOWN
Keywords: TCP proxy ssl http https certificates
Platform: UNKNOWN
Classifier: Development Status :: 2 - Pre-Alpha
Classifier: Topic :: Internet :: Proxy Servers
